.hgtags
TODO
setup.cfg
setup.py
zicbee_lib/__init__.py
zicbee_lib/config.py
zicbee_lib/core.py
zicbee_lib/debug.py
zicbee_lib/downloader.py
zicbee_lib/formats.py
zicbee_lib/parser.py
zicbee_lib/remote_apis.py
zicbee_lib/resources.py
zicbee_lib.egg-info/PKG-INFO
zicbee_lib.egg-info/SOURCES.txt
zicbee_lib.egg-info/dependency_links.txt
zicbee_lib.egg-info/entry_points.txt
zicbee_lib.egg-info/top_level.txt
zicbee_lib/commands/__init__.py
zicbee_lib/commands/command_get.py
zicbee_lib/commands/command_misc.py
zicbee_lib/wasp/__init__.py
zicbee_lib/wasp/core.py